ts_routes/__init__.py
ts_routes/py.typed
ts_routes/serializers.py
ts_routes/management/__init__.py
ts_routes/management/commands/__init__.py
ts_routes/management/commands/dump_routes_resolver.py
ts_routes/templates/ts_routes/_dump/resolver.ts
ts_routes/utils/__init__.py
ts_routes/utils/text.py
django_ts_routes-1.0.0.dist-info/METADATA
django_ts_routes-1.0.0.dist-info/WHEEL
django_ts_routes-1.0.0.dist-info/licenses/LICENSE
django_ts_routes-1.0.0.dist-info/RECORD
