Metadata-Version: 2.3
Name: django-ts-routes
Version: 1.0.0
Summary: Expose and perform reverse lookups of Django URLs in the TypeScript world.
Project-URL: homepage, https://github.com/svengt/django-ts-routes
Project-URL: repository, https://github.com/svengt/django-ts-routes
Author: Sven Groot
License: MIT
Keywords: django,export,reverse,typescript,urls
Classifier: Development Status :: 4 - Beta
Classifier: Environment :: Web Environment
Classifier: Framework :: Django
Classifier: Intended Audience :: Developers
Classifier: License :: OSI Approved :: MIT License
Classifier: Natural Language :: English
Classifier: Programming Language :: Python
Classifier: Programming Language :: Python :: 3
Classifier: Programming Language :: Python :: 3.8
Classifier: Programming Language :: Python :: 3.9
Classifier: Programming Language :: Python :: 3.10
Classifier: Programming Language :: Python :: 3.11
Classifier: Programming Language :: Python :: 3.12
Classifier: Programming Language :: Python :: 3.13
Requires-Python: >=3.8
Requires-Dist: django>=4.2
